LxpApi/__init__.py
LxpApi/lxpapi.py
LxpApi/lxpservice.py
LxpApi/utils.py
lxpservice-0.0.3.dist-info/METADATA
lxpservice-0.0.3.dist-info/WHEEL
lxpservice-0.0.3.dist-info/entry_points.txt
lxpservice-0.0.3.dist-info/top_level.txt
lxpservice-0.0.3.dist-info/RECORD
